lsequbo/__init__.py
lsequbo/ising.py
lsequbo/lsequbo.py
lsequbo-0.0.1.dist-info/METADATA
lsequbo-0.0.1.dist-info/WHEEL
lsequbo-0.0.1.dist-info/RECORD
