Metadata-Version: 2.3
Name: lsequbo
Version: 0.0.1
Summary: QUBO problems for linear systems of equations (LSEs)
Author-email: Orkun Şensebat <git@senseb.at>
Classifier: License :: OSI Approved :: MIT License
Classifier: Operating System :: OS Independent
Classifier: Programming Language :: Python :: 3
Requires-Python: >=3.8
